clovers_tabletop_helper/__init__.py
clovers_tabletop_helper/core.py
clovers_tabletop_helper-0.1.3.dist-info/LICENSE
clovers_tabletop_helper-0.1.3.dist-info/METADATA
clovers_tabletop_helper-0.1.3.dist-info/WHEEL
clovers_tabletop_helper-0.1.3.dist-info/RECORD
